{
  "start_date": "2026-05-28",
  "initial_capital": 10000,
  "cash": 3406.33,
  "positions": [
    {
      "code": "588000",
      "name": "科创50ETF华夏",
      "category": "AI/科技",
      "shares": 2007,
      "cost_price": 1.793,
      "last_price": 1.735,
      "market_value": 3482.15
    },
    {
      "code": "159625",
      "name": "绿色电力ETF嘉实",
      "category": "绿电",
      "shares": 2941,
      "cost_price": 0.85,
      "last_price": 0.908,
      "market_value": 2670.43
    },
    {
      "code": "518880",
      "name": "黄金ETF华安",
      "category": "黄金",
      "shares": 49,
      "cost_price": 10.12,
      "last_price": 9.78,
      "market_value": 479.22
    }
  ],
  "history": [
    {
      "date": "2026-05-28",
      "nav": 10000.00,
      "daily_pnl_pct": 0.0,
      "cumulative_pnl_pct": 0.0,
      "actions": [
        "买入 科创50ETF华夏(588000) 1,666股@¥1.80 | 合计¥2,998.80",
        "买入 绿色电力ETF嘉实(159625) 2,941股@¥0.85 | 合计¥2,499.85",
        "买入 黄金ETF华安(518880) 49股@¥10.12 | 合计¥495.88（底仓5%）"
      ]
    },
    {
      "date": "2026-05-29",
      "nav": 9938.08,
      "daily_pnl_pct": -0.0062,
      "cumulative_pnl_pct": -0.0062,
      "actions": [
        "仓位不动：守仓等换手降温完成（科创50指数实际-5%，与预警吻合）",
        "⚠️ 价格修正(5/30报告)：按实际收盘更新（588000:1.729/-5.0%；159625:0.869/+1.04%；518880:10.13/+0.49%）"
      ]
    },
    {
      "date": "2026-05-30",
      "nav": 9938.08,
      "daily_pnl_pct": 0.0,
      "cumulative_pnl_pct": -0.0062,
      "actions": [
        "周末无交易（A股休市）：维持仓位不动，等待周一成交量信号",
        "DXY跌破99（98.89），黄金半绿灯亮起，金价$4,520距双确认$4,650仍约3-4%"
      ]
    },
    {
      "date": "2026-05-31",
      "nav": 9938.08,
      "daily_pnl_pct": 0.0,
      "cumulative_pnl_pct": -0.0062,
      "actions": [
        "周日无交易（A股休市）：连续第2个休市日，仓位不动",
        "周末催化追踪：华为'韬定律'+LPDDR5X季涨80%（验证算力全链通胀逻辑）",
        "等待周一(6/1)信号：①成交额≤3万亿+588000不破1.70→科创50小加；②伦敦金连续2日>$4,650→黄金试探加至7%"
      ]
    },
    {
      "date": "2026-06-01",
      "nav": 10018.16,
      "daily_pnl_pct": 0.0081,
      "cumulative_pnl_pct": 0.0018,
      "actions": [
        "🟢 买入 科创50ETF华夏(588000) 341股@¥1.757 | 合计¥599.14 | 双信号触发：成交额2.99万亿<3万亿✅+588000收1.757不破1.70✅",
        "科创50仓位：1,666股→2,007股，仓位~29%→~35%，加权成本¥1.793/股",
        "🟡 黄金底仓维持（518880 49股），伦敦金$4,541距触发线$4,650差$109，未触发双确认",
        "🟢 绿电守仓（159625 2,941股），国家电网4万亿十五五投资强化持仓逻辑"
      ]
    },
    {
      "date": "2026-06-02",
      "nav": 9887.03,
      "daily_pnl_pct": -0.0131,
      "cumulative_pnl_pct": -0.0113,
      "actions": [
        "仓位不动：科创50单日重挫约-5%（指数调样+主力切换消费防御），无系统性风险，守仓等企稳",
        "🟡 绿电ETF(159625)随公用事业领涨+1.8%，守仓享受；今日不追涨加仓",
        "🟡 黄金底仓不动，伦敦金约$4,440处于下行趋势，等「连续2日≥$4,450+DXY<100」触发",
        "⚠️ 止损观察：588000若跌破1.60（较今日约再跌-4%），考虑减仓1/3约669股护本"
      ]
    },
    {
      "date": "2026-06-03",
      "nav": 9958.82,
      "daily_pnl_pct": 0.0073,
      "cumulative_pnl_pct": -0.0041,
      "actions": [
        "仓位不动：科创50调样效应持续（6/12生效），小反弹无明确加仓信号，守仓等6/12落地",
        "🟡 绿电ETF(159625)持续强势，无回调至目标位0.88，守仓",
        "🟡 黄金底仓不动，美联储6月降息预期归零，DXY约101，等6/5非农数据评估",
        "⚠️ 价格为估算值（588000≈1.695/159625≈0.902/518880≈10.16），以次日校验数据为准"
      ]
    },
    {
      "date": "2026-06-04",
      "nav": 10021.25,
      "daily_pnl_pct": 0.0063,
      "cumulative_pnl_pct": 0.0021,
      "actions": [
        "仓位不动：AI/算力板块热度延续但科创50调样（6/12）前机械性卖压未完全消化，无明确信号",
        "🟡 绿电ETF(159625)稳健，无回调至目标位0.88-0.89，守仓",
        "🟡 黄金底仓不动，6/5美国5月非农为关键定向事件，今日进入静默期",
        "⚠️ 价格为估算值（588000≈1.720/+1.5%；159625≈0.906/+0.4%；518880≈10.17/+0.1%），以次日校验为准"
      ]
    },
    {
      "date": "2026-06-05",
      "nav": 10086.66,
      "daily_pnl_pct": 0.0065,
      "cumulative_pnl_pct": 0.0087,
      "actions": [
        "⚠️ 本条为估算值（已被6/6日报校正）：实际科创50当日重挫>4%，估算+1.5%严重失真",
        "仓位不动：等非农数据后周末评估",
        "实际收盘（6/6校正）：588000≈1.645（vs估1.746）；159625≈0.895（vs估0.911）；518880≈10.09（vs估10.14）"
      ]
    },
    {
      "date": "2026-06-06",
      "nav": 9834.46,
      "daily_pnl_pct": -0.025,
      "cumulative_pnl_pct": -0.01654,
      "actions": [
        "周六休市，无交易",
        "校正6/5估算价：588000 ¥1.746→¥1.645（科创50实际跌>4%）；159625 ¥0.911→¥0.895（实际-1.7%）；518880 ¥10.14→¥10.09（A股收盘前弱化）",
        "⚠️ 非农强劲(+17.2万)：伦敦金夜间跌3%至$4,340；518880周一将低开约2-3%（预估¥9.79-9.89）",
        "🟡 周一预案：588000>1.65+成交<3万亿→小补100-150股；518880在9.70-9.80企稳→试探补20-30股；否则守仓"
      ]
    },
    {
      "date": "2026-06-07",
      "nav": 9834.46,
      "daily_pnl_pct": 0.0,
      "cumulative_pnl_pct": -0.01654,
      "actions": [
        "周日休市，无交易",
        "黄金国际市场持续走弱：伦敦金周末约$4,329（较周四收盘$4,475跌约-3.3%），周一518880预计低开约3-3.5%至¥9.75-9.80",
        "科创50调样确认：6/12收市后调入华虹公司/源杰科技/摩尔线程/沐曦股份（全为AI算力/国产芯片企业），中期AI纯度大幅提升",
        "修正DXY基准：前日报估DXY 102.5→实际约100-100.5；黄金补仓触发线更新为「DXY<99+伦敦金连续2日>$4,380」",
        "🟡 本周关键日历：6/9开盘30分钟观察信号；6/10美国5月CPI；6/12科创50调样落地；6/18美联储沃什首次议息"
      ]
    },
    {
      "date": "2026-06-08",
      "nav": 9808.63,
      "daily_pnl_pct": -0.0026,
      "cumulative_pnl_pct": -0.01914,
      "actions": [
        "🟡 周一开盘日（修正：本周一实际为6/8，前期日报误标6/9），三仓维持不动，无交易",
        "黄金低开兑现：伦敦金进一步跌至约$4,290（日内低$4,268，较上周四$4,475跌-4.1%），518880估算收约¥9.69（-4.2% vs成本）",
        "🟡 科创50(588000)处6/12调样前换仓压力区，估约¥1.638勉强守住1.63，按不频繁换手原则维持不动，加仓窗口看6/15是否放量",
        "🟢 绿电(159625)资金面强势（同类绿电ETF连续13日净吸金创规模新高+储能Q1出货+139%），守仓估约¥0.898",
        "🔴 黄金底仓坚决不补不摊低成本，等6/10 CPI给方向；触发线「CPI<3.5%+伦敦金连续2日>$4,380+DXY<99」三重确认",
        "⚠️ 价格为估算值（588000≈1.638/159625≈0.898/518880≈9.69），以次日校验数据为准"
      ]
    },
    {
      "date": "2026-06-09",
      "nav": 9867.64,
      "daily_pnl_pct": 0.0060,
      "cumulative_pnl_pct": -0.01324,
      "actions": [
        "三仓维持不动，无交易（CPI前夜，子弹留给6/10）",
        "🟡 科创50(588000)随AI产业链领涨反弹，科创50指数+1.59%，588000估约¥1.663（+1.5%），远离¥1.60止损线；守仓等6/12调样落地+6/15放量，不追高",
        "🟢 绿电(159625)今日资金轮向AI而滞涨，估约¥0.899（约持平）；基本面最稳（储能景气+算电协同），守仓不追，回调0.87-0.88再补",
        "🟡 黄金(518880)随伦敦金从$4,290反抽至$4,340回血，估约¥9.79（+1%）；DXY回落至约99补金半信号点亮，但坚决不抢跑6/10 CPI，等三重确认",
        "⚠️ 价格为估算值（588000≈1.663/159625≈0.899/518880≈9.79），以次日校验数据为准；最大风险为6/10美国5月CPI超预期(3.8%+)引发AI+黄金双杀"
      ]
    },
    {
      "date": "2026-06-10",
      "nav": 9851.73,
      "daily_pnl_pct": -0.0016,
      "cumulative_pnl_pct": -0.01483,
      "actions": [
        "三仓维持不动，无交易（CPI揭晓日，今晚20:30美国5月CPI前不押单边）",
        "🟡 科创50(588000)CPI前夜窄幅走平估约¥1.658（约-0.3%），稳守¥1.60上方；守仓等6/12调样落地+6/15放量",
        "🟢 绿电(159625)结构性轮动中防御属性正常发挥，估约¥0.901（约+0.2%），守仓不追",
        "🔴 黄金(518880)随伦敦金跌破$4,200创三个月新低，估约¥9.55（约-2.5%）；已触及「降仓评估线」但底仓仅4.7%地板，不在CPI前最低点割肉，维持不动、坚决不补",
        "✅ 复盘：上期「黄金坚决不抢跑CPI」纪律躲过$4,340→$4,200急跌；补金半信号(DXY<99)随美元走强熄灭",
        "⚠️ 价格为估算值（588000≈1.658/159625≈0.901/518880≈9.55），以次日校验数据为准；触发线已破暂不执行，若CPI超预期且金价续破$4,150无企稳再评估降地板仓"
      ]
    },
    {
      "date": "2026-06-11",
      "nav": 9811.66,
      "daily_pnl_pct": -0.00407,
      "cumulative_pnl_pct": -0.01883,
      "actions": [
        "三仓维持不动，无交易（CPI落地但为混合信号：整体4.2%破4，核心+0.2%低于预期降温，不押单边）",
        "🟡 科创50(588000)CPI压制下科技分化、半导体强软件弱，估约¥1.650（约-0.5%）稳守¥1.60上方；工信部印发《AI+信息通信》新政托底，守仓等6/12调样落地+6/15放量",
        "🟢 绿电(159625)大盘走弱中防御抗跌，估约¥0.897（约-0.4%）；储能高景气+算电协同，守仓不追，回调0.87-0.88再补",
        "🔴 黄金(518880)随伦敦金脉冲$40又跳水至约$4,090（较$4,200再-2.6%），估约¥9.30；续破「二次确认降仓线」$4,150但因『破4是能源驱动+核心降温+底仓仅4.6%地板』维持不动、坚决不补",
        "⚠️ 黄金硬止损线明确下移并锁死：伦敦金有效跌破$4,023关键支撑→无条件降至2-3%或清地板仓，不再第三次推迟",
        "⚠️ 价格为估算值（588000≈1.650/159625≈0.897/518880≈9.30），以次日校验数据为准；下一关口6/12调样落地、6/15放量、6/17-18议息"
      ]
    },
    {
      "date": "2026-06-12",
      "nav": 9923.79,
      "daily_pnl_pct": 0.01143,
      "cumulative_pnl_pct": -0.00762,
      "actions": [
        "三仓维持不动，无交易（CPI利空出尽、A股普涨、黄金V反，三仓齐回血，但无『干净』加减仓信号，守仓为最优）",
        "✅ 关键复盘胜利：伦敦金6/11盘中急挫至$4,024.19（几乎贴$4,023硬止损线）后强力V反、收$4,210.58(+3.42%)——『不在地板仓最低点割肉』被市场用大阳线验证正确，若昨割在$4,090即卖在黎明前；硬止损$4,023盘中触及未有效跌破，未触发降仓",
        "🟡 科创50(588000)CPI利空出尽+算力主线领涨、CPO概念领涨，估约¥1.690（约+2.4%）远离¥1.60；今晚收市后调样落地(华虹/源杰/摩尔线程/沐曦入列)，守仓等6/15调样生效首日放量再加，今日大涨不追",
        "🟢 绿电(159625)普涨中跟涨估约¥0.904（约+0.8%）；6/11发改委688号文『绿电直连一对多』新政兑现算电协同叙事，守仓不追，回调0.87-0.88再补",
        "🟡 黄金(518880)随伦敦金V反估约¥9.53（约+2.5%）回血；DXY守稳100上方、实际利率高位，属超跌强反弹非趋势反转，地板底仓不动、坚决不追涨，硬止损$4,023保留不变",
        "⚠️ 价格为估算值（588000≈1.690/159625≈0.904/518880≈9.53），以次日校验数据为准；下一关口6/15调样生效首日放量、6/17-18美联储议息"
      ]
    },
    {
      "date": "2026-06-13",
      "nav": 9923.79,
      "daily_pnl_pct": 0.0,
      "cumulative_pnl_pct": -0.00762,
      "actions": [
        "周六休市，无交易：三仓自然不动，价格沿用6/12收盘估值，净值持平¥9,923.79（累计-0.76%）",
        "节假日持仓『最优不动』原则：周末不基于情绪预判，下周一以『放量+北向方向』双信号决定加减仓",
        "✅ 黄金『V反次日不追涨』被周五金价小幅回吐（伦敦金约$4,179/-0.76%）侧面验证——若6/12追高补仓今天即站小亏浮亏位",
        "🟡 下周决策树挂账：①6/15科创50调样生效首日看放量（放量→588000小加至38%上限、缩量→守仓、破¥1.60→减1/3）；②绿电回调0.87-0.88或配储/直供订单公告→评估补；③黄金等『核心通胀回落+连续2日站稳$4,200+DXY破100』三重确认重启补仓，破$4,023降地板仓；④6/17-18美联储新主席首次议息看措辞鹰鸽",
        "⚠️ 价格沿用6/12估算（588000≈1.690/159625≈0.904/518880≈9.53），6/15开盘后以实际成交价校验，尤其黄金ETF滞后伦敦金夜盘的老盲区需重新mark"
      ]
    },
    {
      "date": "2026-06-14",
      "nav": 9923.79,
      "daily_pnl_pct": 0.0,
      "cumulative_pnl_pct": -0.00762,
      "actions": [
        "周日休市，无交易：连续第二个休市日，三仓自然不动，价格沿用6/12收盘估值，净值持平¥9,923.79（累计-0.76%）",
        "节假日持仓『最优不动』原则延续：周末不基于情绪预判，6/15以『放量+北向方向』双信号决定加减仓",
        "✅ 黄金『V反次日不追涨』继续验证：周五现货黄金周收约$4,218受中东和平预期推动高位整固、未续创新高（阻力$4,318仍远），属消息面反弹非趋势反转",
        "🟡 下周『央行超级周』决策树挂账：①6/15科创50调样生效首日看放量（放量→588000小加至38%上限、缩量→守仓、破¥1.60→减1/3）；②绿电回调0.87-0.88或配储/直供订单公告→评估补，6/18并网新规利好储能；③黄金等『核心通胀回落+连续2日站稳$4,250+DXY破100』三重确认重启补仓，破$4,023降地板仓；④6/17-18沃什首次议息（维持利率概率96.2%）看措辞鹰鸽",
        "⚠️ 价格沿用6/12估算（588000≈1.690/159625≈0.904/518880≈9.53），6/15开盘后以实际成交价校验，尤其黄金ETF滞后伦敦金夜盘的老盲区需重新mark"
      ]
    },
    {
      "date": "2026-06-15",
      "nav": 9877.55,
      "daily_pnl_pct": -0.00466,
      "cumulative_pnl_pct": -0.01224,
      "actions": [
        "三仓维持不动，无交易：科创50调样生效后首个完整交易日『利好兑现即回吐』——上证-0.64%、科技回调、大盘价值领涨，未走出『放量上涨』故按既定纪律『不放量则不追、守仓不减』，588000估约¥1.665远在¥1.60止损线上方约4%",
        "✅ 复盘胜利：『调样生效首日看放量、不放量则守仓不追』双信号纪律被市场直接验证——调样明牌被6/12大涨抢跑、靴子落地即获利了结，昨天没机械加仓正确，避免买在回吐高点",
        "🟢 绿电(159625)大盘价值领涨格局下防御抗跌估约¥0.905（约持平/小涨）；6/18《分布式电源接入承载力评估导则》正式实施，『配储提升可开放容量』利好储能，守仓不追、回调0.87-0.88再补",
        "🟡 黄金(518880)美伊达成和平协议、霍尔木兹海峡将通航、避险降温——本是利空消息面但金价仅高位震荡约$4,217(+0.15%)未深跌，印证V反是超跌强反弹非趋势反转，地板底仓不动、不追涨、不割肉，硬止损$4,023保留不变",
        "⚠️ 价格为盘后估算（588000≈1.665/159625≈0.905/518880≈9.55），以行情软件实际收盘为准，黄金ETF滞后伦敦金夜盘老盲区仍在；本周头号裁决点6/17-18美联储沃什首次议息（维持利率概率约96%）看措辞鹰鸽，偏鹰则AI+黄金可能双杀、偏鸽则共振修复"
      ]
    },
    {
      "date": "2026-06-16",
      "nav": 9879.76,
      "daily_pnl_pct": 0.00022,
      "cumulative_pnl_pct": -0.01202,
      "actions": [
        "三仓维持不动，无交易：议息前夜（6/17-18美联储沃什首次议息，决议北京时间6/18 02:00）守仓为最优，约34.5%现金子弹完整",
        "❌ 复盘修正：昨天判断『美伊和平、避险降温、金价或重测$4,125-4,180』方向看错——现货黄金昨夜美盘强势突破+3%至约$4,345-4,350，一举站上$4,250阻力线（催化：地缘升级委内瑞拉/莫斯科+降息预期回暖）；但『地板仓不动、不在低位割肉』操作对了，正好吃到突破，518880补涨修正至估约¥9.80",
        "🟡 黄金(518880)突破$4,250是补仓三重确认第一重亮灯，但只是站上第一日、DXY破100与核心通胀回落未确认、且明天议息二元裁决——坚决不在+3%脉冲高点/议息前夜追金，地板底仓守仓享浮亏修复，硬止损$4,023保留不变（金价已远离）",
        "🟡 AI(588000)议息前缩量观望、科技与有色跷跷板，估约¥1.66（约-0.3%）稳守¥1.60上方约4%，按『不放量不追、守仓不减』维持，等议息后看放量",
        "🟢 绿电(159625)防御走平估约¥0.905；6/18《分布式电源接入承载力评估导则》正式实施利好储能+算电协同，守仓不追、回调0.87-0.88再补",
        "⚠️ 价格为盘后估算（588000≈1.660/159625≈0.905/518880≈9.80），以行情软件实际收盘为准；6/18议息偏鹰则黄金脉冲突破可能快速回吐(重演6/12 V反后回落)+AI承压，偏鸽/确认降息路径则评估黄金补仓多重确认+AI修复"
      ]
    },
    {
      "date": "2026-06-17",
      "nav": 10012.67,
      "daily_pnl_pct": 0.01345,
      "cumulative_pnl_pct": 0.00127,
      "actions": [
        "三仓维持不动，无交易：议息当天（今晚北京时间6/18 02:00沃什首次议息揭晓）守仓为最优，约34%现金子弹完整，净值今天重新站上¥10,000、累计转正(+0.13%)",
        "✅ 复盘胜利：昨天『议息前守仓不减、不追金』今天被完整验证——A股科技抢跑式大反弹，科创50指数大涨约+4%(光通信/半导体/AI算力领涨)，守仓588000完整吃到+4%(估¥1.660→¥1.725)，是净值跳升+1.35%的唯一功臣；黄金横盘『不追金』既没踏空也没站岗",
        "🟡 AI(588000)放量大涨+4%是议息揭晓前的抢跑反弹，估约¥1.725远在¥1.60上方约8%——『不放量不追』纪律的另一半是『不在+4%脉冲高点/议息前追高』，今晚议息二元裁决前坚决不加，守仓已足；需『议息不鹰+次日不回吐』才小加至38%上限",
        "🟡 黄金(518880)高位整固约$4,330-4,342(连涨4日后横盘)，估约¥9.79走平；『全年不降息』鹰派共识(超七成机构预计2026全年维持3.50-3.75%不降息)是金价最大逆风，议息前不追不割，地板底仓守仓，硬止损$4,023保留不变(已远离)，补仓需『议息不鹰+DXY破99.50+站稳$4,300』多重确认",
        "🟢 绿电(159625)科技领涨日防御走平估约¥0.906；6/18《分布式电源接入承载力评估导则》正式实施利好储能+算电协同，守仓不追、回调0.87-0.88再补",
        "⚠️ 价格为盘后估算（588000≈1.725/159625≈0.906/518880≈9.79），以行情软件实际收盘为准；今晚议息偏鹰/点阵图删降息则今天+4%抢跑的AI与高位黄金可能双双回吐，偏鸽/保留降息路径则评估AI加仓+黄金补仓多重确认"
      ]
    },
    {
      "date": "2026-06-18",
      "nav": 10038.13,
      "daily_pnl_pct": 0.00254,
      "cumulative_pnl_pct": 0.00381,
      "actions": [
        "三仓维持不动，无交易：美联储沃什首秀『鹰派满贯』落地（12:0维持3.50-3.75%，删降息前瞻指引+点阵图转向年内可能加息+通胀预期上调至3.6%），但A股与黄金双双抗住未现双杀，守仓不动为唯一最优解，约33.9%现金子弹完整，净值续创新高(+0.38%)",
        "✅ 复盘大胜：昨天『不在+4%脉冲高点/议息前追买AI与黄金』今天被验证为最大胜利——议息果然偏鹰，若昨天追AI或追金即买在利空落地山顶；守仓不减则吃到今天抗跌、净值创新高",
        "⚠️ 预判修正：『偏鹰则AI+黄金双杀』过于线性，低估『利空出尽』效应——鹰派早被『全年不降息』共识充分定价，靴子落地反成利空出尽；教训：二元事件可预判结果方向、但难预判市场反应幅度",
        "🟡 AI(588000)鹰派逆风下逆势抗住，科创50指数+0.58%，估约¥1.735(+0.6%)远在¥1.60上方约8%——但加仓前提『议息不鹰』已被点阵图转向加息彻底证伪，加仓逻辑链断裂，本周守仓不减不加，等鹰派定价消化后全新信号；6/19收盘二次确认抗跌真假",
        "🟡 黄金(518880)鹰派后意外守在$4,320-4,330估约¥9.78(走平)，核心是DXY 99.48未能向上突破99.50；补仓三重确认里『议息不鹰』已熄灭，不追不补不割，地板底仓守仓，硬止损$4,023保留不变(已远离)",
        "🟢 绿电(159625)防御走平估约¥0.908；6/18《分布式电源接入承载力评估导则》正式实施利好储能+算电协同+低鹰派敏感度，是组合减震器，守仓不追、回调0.87-0.88再补",
        "⚠️ 价格为盘后估算（588000≈1.735/159625≈0.908/518880≈9.78），以行情软件实际收盘为准；今天为鹰派利空落地第一天的抗跌，真正考验是6/19『次日不回吐』——鹰派点阵图(年内可能加息+通胀3.6%)意味实际利率长期上行压力未消，若DXY后续破99.50则今天扛住的AI与黄金仍可能补跌"
      ]
    }
  ]
}
